py_fake_server/__init__.py
py_fake_server/endpoint.py
py_fake_server/request.py
py_fake_server/response.py
py_fake_server/route.py
py_fake_server/server.py
py_fake_server/statistic.py
py_fake_server/validators.py
py_fake_server-0.2.1.dist-info/METADATA
py_fake_server-0.2.1.dist-info/RECORD
py_fake_server-0.2.1.dist-info/WHEEL
py_fake_server-0.2.1.dist-info/top_level.txt
