Metadata-Version: 2.1
Name: py-fake-server
Version: 0.2.1
Summary: Make fake servers with pleasure!
Home-page: https://github.com/Telichkin/py_fake_server
Author: Roman Telichkin
Author-email: roman@telichk.in
License: MIT
Platform: UNKNOWN
Classifier: Programming Language :: Python :: 3.6
Classifier: Topic :: Software Development :: Libraries :: Python Modules
Requires-Dist: WebTest (==2.0.28)
Requires-Dist: falcon (==1.2.0)
Requires-Dist: falcon-multipart (==0.2.0)
